abhinav_greeting/__init__.py
abhinav_greeting-0.6.dist-info/licenses/LICENSE
abhinav_greeting-0.6.dist-info/METADATA
abhinav_greeting-0.6.dist-info/WHEEL
abhinav_greeting-0.6.dist-info/top_level.txt
abhinav_greeting-0.6.dist-info/RECORD
