Metadata-Version: 2.4
Name: abhinav_greeting
Version: 0.6
Summary: A simple Python package that provides personalized greetings.
Home-page: https://github.com/abhinav-aligne/abhinav_greeting
Author: Abhinav Gera
Author-email: abhinav.gera@aligne.ai
Classifier: Programming Language :: Python :: 3
Classifier: License :: OSI Approved :: MIT License
Classifier: Operating System :: OS Independent
Requires-Python: >=3.6
License-File: LICENSE
Dynamic: author
Dynamic: author-email
Dynamic: classifier
Dynamic: description
Dynamic: description-content-type
Dynamic: home-page
Dynamic: license-file
Dynamic: requires-python
Dynamic: summary
